{
  "success": true,
  "code": 0,
  "data": [
    {
      "id": "110100",
      "name": "北京市",
      "parentid": "110000",
      "simple": "北京",
      "level": 2,
      "code": "010",
      "mergername": "中国,北京,北京市",
      "pinyin": "Beijing",
      "ing": "116.405285",
      "lat": "39.904989",
      "sysHospitals": [
        {
          "id": "MD_wusi",
          "name": "广渠店",
          "address": "北京市东城区广渠门内大街41号雍贵中心B座301（电梯直达三层，右转即到）",
          "cityId": "110100",
          "lat": "39.89418",
          "lng": "116.42909"
        },
        {
          "id": "MD_guanshe",
          "name": "官舍店",
          "address": "朝阳区东方东路19号5号楼官舍商场三层 （燕莎友谊商城北面，亮马桥东北角）",
          "cityId": "110100",
          "lat": "39.9505",
          "lng": "116.46394"
        },
        {
          "id": "MD_meilun",
          "name": "美仑店",
          "address": "朝阳区科荟路51号院美伦堡小区西门13号楼，北师大朝阳附中对面",
          "cityId": "110100",
          "lat": "40.01122",
          "lng": "116.36954"
        }
      ]
    },
    {
      "id": "310100",
      "name": "上海市",
      "parentid": "310000",
      "simple": "上海",
      "level": 2,
      "code": "021",
      "mergername": "中国,上海,上海市",
      "pinyin": "Shanghai",
      "ing": "121.472644",
      "lat": "31.231706",
      "sysHospitals": [
        {
          "id": "MD_shanghai",
          "name": "隆昌店",
          "address": "上海市杨浦区隆昌路586号复旦软件园1楼A8-2楼A6（近长阳路口，地铁12号线隆昌路站4号出口）",
          "cityId": "310100",
          "lat": "31.275304",
          "lng": "121.543846"
        }
      ]
    },
    {
      "id": "420100",
      "name": "武汉市",
      "parentid": "420000",
      "simple": "武汉",
      "level": 2,
      "code": "",
      "mergername": "中国,湖北省,武汉市",
      "pinyin": "Wuhan",
      "ing": "114.298572",
      "lat": "30.584355",
      "sysHospitals": [
        {
          "id": "MD_huaqiao",
          "name": "华侨城店",
          "address": "洪山区欢乐大道华侨城商业街S3栋",
          "cityId": "420100",
          "lat": "30.58949",
          "lng": "114.38565"
        }
      ]
    },
    {
      "id": "440100",
      "name": "广州市",
      "parentid": "440000",
      "simple": "广州",
      "level": 2,
      "code": "020",
      "mergername": "中国,广东省,广州市",
      "pinyin": "Guangzhou",
      "ing": "113.280637",
      "lat": "23.125178",
      "sysHospitals": [
        {
          "id": "MD_huacheng",
          "name": "花城店",
          "address": "天河区花城大道88号优托邦2座首层130A，花城大道与猎德大道交汇处西南角(5号线猎德站A出口)",
          "cityId": "440100",
          "lat": "23.117494",
          "lng": "113.332949"
        },
        {
          "id": "MD_panyu",
          "name": "番禺店",
          "address": "番禺区番禺大道海印又一城B座总统大酒店首层（正安中医）",
          "cityId": "440100",
          "lat": "22.99998",
          "lng": "113.34867"
        }
      ]
    },
    {
      "id": "440300",
      "name": "深圳市",
      "parentid": "440000",
      "simple": "深圳",
      "level": 2,
      "code": "0755",
      "mergername": "中国,广东省,深圳市",
      "pinyin": "Shenzhen",
      "ing": "114.085947",
      "lat": "22.547",
      "sysHospitals": [
        {
          "id": "MD_shucheng",
          "name": "福田店（原书城店）",
          "address": "深圳市福田区福华路319号兆邦基金融大厦4楼（地铁1号线岗厦C出口左侧，从大厦的7、8、9号电梯上楼）",
          "cityId": "440300",
          "lat": "22.54561",
          "lng": "114.05969"
        },
        {
          "id": "MD_nanshan",
          "name": "南山店",
          "address": "南山区金鸡路1号田厦·翡翠明珠裙楼七巧国二层（南山图书馆旁）",
          "cityId": "440300",
          "lat": "22.53408",
          "lng": "113.92284"
        }
      ]
    },
    {
      "id": "510100",
      "name": "成都市",
      "parentid": "510000",
      "simple": "成都",
      "level": 2,
      "code": "028",
      "mergername": "中国,四川省,成都市",
      "pinyin": "Chengdu",
      "ing": "104.065735",
      "lat": "30.659462",
      "sysHospitals": [
        {
          "id": "MD_kuanzhaizi",
          "name": "宽窄巷子店",
          "address": "青羊区下同仁路9号2楼(近地铁通惠门站)",
          "cityId": "510100",
          "lat": "30.6625",
          "lng": "104.05039"
        }
      ]
    },
    {
      "id": "530100",
      "name": "昆明市",
      "parentid": "530000",
      "simple": "昆明",
      "level": 2,
      "code": "0871",
      "mergername": "中国,云南省,昆明市",
      "pinyin": "Kunming",
      "ing": "102.712251",
      "lat": "25.040609",
      "sysHospitals": [
        {
          "id": "MD_yunxi",
          "name": "云玺店",
          "address": "官渡区昌宏西路6689号云玺大宅商业街A102-A106",
          "cityId": "530100",
          "lat": "24.94323",
          "lng": "102.71947"
        }
      ]
    }
  ],
  "total": 0
}